babycat-0.0.15.dist-info/METADATA
babycat-0.0.15.dist-info/WHEEL
babycat-0.0.15.dist-info/license_files/LICENSE
babycat/__init__.py
babycat/babycat.abi3.so
babycat-0.0.15.dist-info/RECORD
