Metadata-Version: 2.1
Name: babycat
Version: 0.0.15
Classifier: License :: OSI Approved :: MIT License
Classifier: Intended Audience :: Developers
Classifier: Programming Language :: Rust
Classifier: Operating System :: POSIX :: Linux
Classifier: Operating System :: Microsoft :: Windows
Classifier: Operating System :: MacOS
Classifier: Topic :: Multimedia :: Sound/Audio :: Analysis
Classifier: Topic :: Multimedia :: Sound/Audio :: Conversion
Requires-Dist: numpy >= 1.16.0
License-File: LICENSE
Summary: An audio decoding and manipulation library, with bindings for C, Python, and WebAssembly.
Home-Page: https://babycat.io
Author: Neocrym Records Inc. <engineering@neocrym.com>
Author-email: Neocrym Records Inc. <engineering@neocrym.com>
License: MIT
Project-URL: Source Code, https://github.com/babycat-io/babycat
